votes/__init__.py
votes/admin.py
votes/api.py
votes/compat.py
votes/managers.py
votes/models.py
votes/serializers.py
votes/urls.py
votes/utils.py
votes/views.py
votes/migrations/0001_initial.py
votes/migrations/0002_vote_vote.py
votes/migrations/__init__.py
votes/static/css/votes.css
votes/static/js/votes.js
votes/templates/votes/base.html
votes/tests/__init__.py
votes/tests/test_api.py
votes/tests/test_models.py
votes-1.0.1.dist-info/DESCRIPTION.rst
votes-1.0.1.dist-info/METADATA
votes-1.0.1.dist-info/metadata.json
votes-1.0.1.dist-info/RECORD
votes-1.0.1.dist-info/top_level.txt
votes-1.0.1.dist-info/WHEEL
