Metadata-Version: 1.1
Name: votes
Version: 1.0.1
Summary: DRF Vote is a simple Django Rest Framework app to add ability to like/dislike a model.
Home-page: https://github.com/tixdo/votes
Author: ayush jain
Author-email: ayush.jain@consultadd.in
License: BSD
Keywords: votes
Platform: UNKNOWN
Classifier: Development Status :: 3 - Alpha
Classifier: Framework :: Django
Classifier: Framework :: Django :: 1.8
Classifier: Framework :: Django :: 1.9
Classifier: Intended Audience :: Developers
Classifier: License :: OSI Approved :: BSD License
Classifier: Natural Language :: English
Classifier: Programming Language :: Python :: 2
Classifier: Programming Language :: Python :: 2.7
Classifier: Programming Language :: Python :: 3
Classifier: Programming Language :: Python :: 3.3
Classifier: Programming Language :: Python :: 3.4
Classifier: Programming Language :: Python :: 3.5
